atchatbot/__init__.py
atchatbot/chatbot.py
atchatbot/core.py
atchatbot/intent_detector.py
atchatbot/parser.py
atchatbot/response_generator.py
atchatbot/utils.py
atchatbot-0.4.2.dist-info/licenses/LICENSE
atchatbot-0.4.2.dist-info/METADATA
atchatbot-0.4.2.dist-info/WHEEL
atchatbot-0.4.2.dist-info/top_level.txt
atchatbot-0.4.2.dist-info/RECORD
